fluent_chaining/__init__.py
fluent_chaining/core.py
fluent_chaining/operations.py
fluent_chaining/option.py
fluent_chaining/result.py
fluent_chaining-0.1.0.dist-info/licenses/LICENSE
fluent_chaining-0.1.0.dist-info/METADATA
fluent_chaining-0.1.0.dist-info/WHEEL
fluent_chaining-0.1.0.dist-info/top_level.txt
fluent_chaining-0.1.0.dist-info/RECORD
