Metadata-Version: 2.4
Name: fluent-chaining
Version: 0.1.0
Summary: A Python package for pure functional programming with fluent chaining that reads like prose
Author-email: Project-Saturday <contact@project-saturday.org>
License: MIT
Project-URL: Homepage, https://github.com/Project-Saturday/fluent-chaining
Project-URL: Bug Reports, https://github.com/Project-Saturday/fluent-chaining/issues
Project-URL: Source, https://github.com/Project-Saturday/fluent-chaining
Keywords: functional,chaining,fluent,pure-functions,compose
Classifier: Development Status :: 3 - Alpha
Classifier: Intended Audience :: Developers
Classifier: License :: OSI Approved :: MIT License
Classifier: Programming Language :: Python :: 3
Classifier: Programming Language :: Python :: 3.9
Classifier: Programming Language :: Python :: 3.10
Classifier: Programming Language :: Python :: 3.11
Classifier: Programming Language :: Python :: 3.12
Classifier: Programming Language :: Python :: 3.13
Classifier: Topic :: Software Development :: Libraries :: Python Modules
Classifier: Topic :: Utilities
Requires-Python: >=3.9
License-File: LICENSE
Provides-Extra: dev
Requires-Dist: pytest>=7.0; extra == "dev"
Requires-Dist: pytest-cov>=4.0; extra == "dev"
Requires-Dist: black>=25.0; extra == "dev"
Requires-Dist: isort>=5.0; extra == "dev"
Requires-Dist: flake8>=5.0; extra == "dev"
Requires-Dist: mypy>=1.0; extra == "dev"
Requires-Dist: bandit>=1.7.0; extra == "dev"
Requires-Dist: safety>=2.0.0; extra == "dev"
Requires-Dist: pre-commit>=3.0.0; extra == "dev"
Dynamic: license-file
